{
  "uuid": "92c06a89-5c53-4e5a-a2fd-338e5e9efcaf",
  "lastMigration": 19,
  "name": "Shongo API",
  "endpointPrefix": "api/v1/",
  "latency": 0,
  "port": 8001,
  "hostname": "0.0.0.0",
  "routes": [
    {
      "uuid": "669ef3be-da6a-4f2c-87f7-6ab64bb1670b",
      "documentation": "Returns different parameters based on \"type\" parameter (VIRTUAL_ROOM, PHYSICAL_RESOURCE, ROOM_CAPACITY).",
      "method": "get",
      "endpoint": "reservation_requests",
      "responses": [
        {
          "uuid": "ef3ed42c-b6b0-4ca1-99a2-34af4bfaa3c3",
          "body": "{\n  \"count\": 1,\n  \"items\": [\n    {\n      \"id\": \"shongo:meetings.cesnet.cz:req:3\",\n      \"description\": \"Capacity reservation\",\n      \"createdAt\": \"2021-11-03T18:38:09.546Z\",\n      \"lastReservationId\": \"1\",\n      \"state\": \"FAILED\",\n      \"isWritable\": true,\n      \"isProvidable\": true,\n      \"notifyParticipants\": true,\n      \"ownerName\": \"Michal Drobnak\",\n      \"ownerEmail\": \"493239@muni.cz\",\n      \"slot\": {\n        \"start\": \"2021-11-04T15:30:00.000Z\",\n        \"end\": \"2021-11-04T16:30:00.000Z\"\n      },\n      \"futureSlotCount\": 5,\n      \"isDeprecated\": false,\n      \"type\": \"ROOM_CAPACITY\",\n      \"roomCapacityData\": {\n        \"roomName\": \"Some room\",\n        \"roomReservationRequestId\": \"shongo:meetings.cesnet.cz:req:1\",\n        \"roomParticipantCount\": 5\n      }\n    }\n  ]\n}",
          "latency": 0,
          "statusCode": 200,
          "label": "",
          "headers": [],
          "filePath": "",
          "sendFileAsBody": false,
          "rules": [
            {
              "target": "params",
              "modifier": "roomReservationRequestId",
              "value": "shongo:meetings.cesnet.cz:req:1",
              "operator": "equals"
            }
          ],
          "rulesOperator": "OR",
          "disableTemplating": false,
          "fallbackTo404": false
        },
        {
          "uuid": "6fc99030-0edf-41c8-9cd5-fdc58583097a",
          "body": "{{# switch (queryParam 'type')}}\n  {{# case \"VIRTUAL_ROOM\" }}\n    {\n      \"count\": 1,\n      \"items\": [\n        {\n          \"id\": \"shongo:meetings.cesnet.cz:req:1\",\n          \"description\": \"A virtual room reservation.\",\n          \"createdAt\": \"2021-11-03T18:38:09.546Z\",\n          \"state\": \"FAILED\",\n          \"isWritable\": true,\n          \"isProvidable\": true,\n          \"notifyParticipants\": true,\n          \"ownerName\": \"Michal Drobnak\",\n          \"ownerEmail\": \"493239@muni.cz\",\n          \"slot\": {\n            \"start\": \"2021-11-04T15:30:00.000Z\",\n            \"end\": \"2021-11-04T16:30:00.000Z\"\n          },\n          \"futureSlotCount\": 5,\n          \"isDeprecated\": false,\n          \"type\": \"VIRTUAL_ROOM\",\n          \"virtualRoomData\": {\n            \"technology\": \"PEXIP\",\n            \"roomName\": \"Some room\",\n            \"roomParticipantCount\": 5,\n            \"roomHasRecordingService\": true,\n            \"roomHasRecordings\": false,\n            \"isRecordingActive\": false\n          }\n        }\n      ]\n    }\n  {{/ case }}\n  {{# case \"PHYSICAL_RESOURCE\" }}\n    {\n      \"count\": 1,\n      \"items\": [\n        {\n          \"id\": \"shongo:meetings.cesnet.cz:req:2\",\n          \"description\": \"Physical resource reservation\",\n          \"createdAt\": \"2021-11-03T18:38:09.546Z\",\n          \"lastReservationId\": \"1\",\n          \"state\": \"FAILED\",\n          \"isWritable\": true,\n          \"isProvidable\": true,\n          \"notifyParticipants\": true,\n          \"ownerName\": \"Michal Drobnak\",\n          \"ownerEmail\": \"493239@muni.cz\",\n          \"slot\": {\n            \"start\": \"2021-11-04T15:30:00.000Z\",\n            \"end\": \"2021-11-04T16:30:00.000Z\"         \n          },\n          \"futureSlotCount\": 5,\n          \"isDeprecated\": false,\n          \"type\": \"PHYSICAL_RESOURCE\",\n          \"physicalResourceData\": {\n            \"resourceName\": \"Gotex zasedacka G314\",\n            \"resourceDescription\": \"Zasedaci mistnost\"\n          }\n        }\n      ]\n    }\n  {{/ case }}\n  {{# case \"ROOM_CAPACITY\" }}\n    {\n      \"count\": 1,\n      \"items\": [\n        {\n          \"id\": \"shongo:meetings.cesnet.cz:req:3\",\n          \"description\": \"Capacity reservation\",\n          \"createdAt\": \"2021-11-03T18:38:09.546Z\",\n          \"lastReservationId\": \"1\",\n          \"state\": \"FAILED\",\n          \"isWritable\": true,\n          \"isProvidable\": true,\n          \"notifyParticipants\": true,\n          \"ownerName\": \"Michal Drobnak\",\n          \"ownerEmail\": \"493239@muni.cz\",\n          \"slot\": {\n            \"start\": \"2021-11-04T15:30:00.000Z\",\n            \"end\": \"2021-11-04T16:30:00.000Z\"\n          },\n          \"futureSlotCount\": 5,\n          \"isDeprecated\": false,\n          \"type\": \"ROOM_CAPACITY\",\n          \"roomCapacityData\": {\n            \"roomName\": \"Some room\",\n            \"roomReservationRequestId\": \"shongo:meetings.cesnet.cz:req:2\",\n            \"roomParticipantCount\": 5\n          }\n        }\n      ]\n    }\n  {{/ case}}\n  {{# default }}\n    {\n      \"count\": 3,\n      \"items\": [\n        {\n          \"id\": \"shongo:meetings.cesnet.cz:req:1\",\n          \"description\": \"A virtual room reservation.\",\n          \"createdAt\": \"2021-11-03T18:38:09.546Z\",\n          \"lastReservationId\": \"1\",\n          \"state\": \"FAILED\",\n          \"isWritable\": true,\n          \"isProvidable\": true,\n          \"notifyParticipants\": true,\n          \"ownerName\": \"Michal Drobnak\",\n          \"ownerEmail\": \"493239@muni.cz\",\n          \"slot\": {\n            \"start\": \"2021-11-04T15:30:00.000Z\",\n            \"end\": \"2021-11-04T16:30:00.000Z\"\n          },\n          \"futureSlotCount\": 5,\n          \"isDeprecated\": false,\n          \"type\": \"VIRTUAL_ROOM\",\n          \"virtualRoomData\": {\n            \"technology\": \"PEXIP\",\n            \"roomName\": \"Some room\",\n            \"roomParticipantCount\": 5,\n            \"roomHasRecordingService\": true,\n            \"roomHasRecordings\": false,\n            \"isRecordingActive\": false\n          }\n        },\n        {\n          \"id\": \"shongo:meetings.cesnet.cz:req:2\",\n          \"description\": \"Physical resource reservation\",\n          \"createdAt\": \"2021-11-03T18:38:09.546Z\",\n          \"lastReservationId\": \"1\",\n          \"state\": \"FAILED\",\n          \"isWritable\": true,\n          \"isProvidable\": true,\n          \"notifyParticipants\": true,\n          \"ownerName\": \"Michal Drobnak\",\n          \"ownerEmail\": \"493239@muni.cz\",\n          \"slot\": {\n            \"start\": \"2021-11-04T15:30:00.000Z\",\n            \"end\": \"2021-11-04T16:30:00.000Z\"\n          },\n          \"futureSlotCount\": 5,\n          \"isDeprecated\": false,\n          \"type\": \"PHYSICAL_RESOURCE\",\n          \"physicalResourceData\": {\n            \"resourceName\": \"Idk\",\n            \"resourceDescription\": \"Ohoho\"\n          }\n        },\n        {\n          \"id\": \"shongo:meetings.cesnet.cz:req:3\",\n          \"description\": \"Capacity reservation\",\n          \"createdAt\": \"2021-11-03T18:38:09.546Z\",\n          \"lastReservationId\": \"1\",\n          \"state\": \"FAILED\",\n          \"isWritable\": true,\n          \"isProvidable\": true,\n          \"notifyParticipants\": true,\n          \"ownerName\": \"Michal Drobnak\",\n          \"ownerEmail\": \"493239@muni.cz\",\n          \"slot\": {\n            \"start\": \"2021-11-04T15:30:00.000Z\",\n            \"end\": \"2021-11-04T16:30:00.000Z\"\n          },\n          \"futureSlotCount\": 5,\n          \"isDeprecated\": false,\n          \"type\": \"ROOM_CAPACITY\",\n          \"roomCapacityData\": {\n            \"roomName\": \"Some room\",\n            \"roomReservationRequestId\": \"shongo:meetings.cesnet.cz:req:2\",\n            \"roomParticipantCount\": 5\n          }\n        }\n      ]\n    }\n  {{/ default }}\n{{/ switch}}\n",
          "latency": 0,
          "statusCode": 200,
          "label": "",
          "headers": [],
          "filePath": "",
          "sendFileAsBody": false,
          "rules": [
            {
              "target": "query",
              "modifier": "roomReservationRequestId",
              "value": "",
              "operator": "null"
            }
          ],
          "rulesOperator": "OR",
          "disableTemplating": false,
          "fallbackTo404": false
        }
      ],
      "enabled": true,
      "randomResponse": false,
      "sequentialResponse": false
    },
    {
      "uuid": "9df8aa67-d6b5-49f6-bc46-b1bd0afa60ac",
      "documentation": "Additional data: authorizedData (Look inside RoomController > handleListRoomData), allocation and executableState (listing all returns only overall state which you can get by calling ReservationRequestState.fromApi(reservationRequest)), childRequests - these are request made due to periodicity, history - these are requests that moidify the parent request (find more in DetailReservationRequestController > handleDetailReservationRequestTab), periodicity - repeating of reservation (look inside ReservationRequestModel)",
      "method": "get",
      "endpoint": "reservation_requests/:id",
      "responses": [
        {
          "uuid": "395bcc02-004f-455a-9858-c605cf235b3d",
          "body": "{{# switch (urlParam 'id') }}\n  {{# case \"shongo:meetings.cesnet.cz:req:1\" }}\n    {\n      \"id\": \"shongo:meetings.cesnet.cz:req:1\",\n      \"description\": \"A virtual room reservation.\",\n      \"createdAt\": \"2021-11-03T18:38:09.546Z\",\n      \"state\": \"FAILED\",\n      \"allocationState\": \"FAILED\",\n      \"executableState\": \"FAILED\",\n      \"isWritable\": true,\n      \"isProvidable\": true,\n      \"notifyParticipants\": true,\n      \"ownerName\": \"Michal Drobnak\",\n      \"ownerEmail\": \"493239@muni.cz\",\n      \"slot\": {\n        \"start\": \"2021-11-04T15:30:00.000Z\",\n        \"end\": \"2021-11-04T16:30:00.000Z\"\n      },\n      \"periodicity\": {\n        \"type\": \"WEEKLY\",\n        \"periodicityEnd\": \"2021-11-04T15:30:00.000Z\",\n        \"periodicDaysInWeek\": [\"MONDAY\", \"TUESDAY\"],\n        \"periodicityCycle\": 1,\n        \"excludeDates\": [\n          \"2021-11-04\"\n        ]\n      },\n      \"futureSlotCount\": 5,\n      \"isDeprecated\": false,\n      \"type\": \"VIRTUAL_ROOM\",\n      \"virtualRoomData\": {\n        \"technology\": \"PEXIP\",\n        \"roomName\": \"Some room\",\n        \"roomParticipantCount\": 5,\n        \"roomHasRecordingService\": true,\n        \"roomHasRecordings\": false,\n        \"isRecordingActive\": true\n      },\n      \"authorizedData\": {\n        \"pin\": \"12345\",\n        \"adminPin\": \"56789\",\n        \"guestPin\": \"478\",\n        \"allowGuests\": true,\n        \"aliases\": {\n          \"H323/SIP/PhoneNumber\": \"(00420)950087050\",\n          \"H.323 IP\": \"78.128.216.82 050#\"\n        }\n      },\n      \"history\": [\n        {\n          \"id\": \"shongo:meetings.cesnet.cz:req:1\",\n          \"createdAt\": \"2021-11-03T18:38:09.546Z\",\n          \"createdBy\": \"Michal Drobnak\",\n          \"type\": \"MODIFIED\",\n          \"allocationState\": \"ERROR\",\n          \"state\": \"ERROR\",\n          \"isActive\": true,\n          \"isLatestAllocated\": false\n        },\n        {\n          \"id\": \"shongo:meetings.cesnet.cz:req:5\",\n          \"createdAt\": \"2021-11-04T15:21:00.546Z\",\n          \"createdBy\": \"Michal Drobnak\",\n          \"type\": \"NEW\",\n          \"allocationState\": \"ERROR\",\n          \"state\": \"ERROR\",\n          \"isActive\": true,\n          \"isLatestAllocated\": true\n        }\n      ]\n    }\n  {{/ case }}\n  {{# case \"shongo:meetings.cesnet.cz:req:2\" }}\n    {\n      \"id\": \"shongo:meetings.cesnet.cz:req:2\",\n      \"lastReservationId\": null,\n      \"parentRequestId\": null,\n      \"description\": \"A meeting room reservation.\",\n      \"createdAt\": \"2021-11-03T18:38:09.546Z\",\n      \"state\": \"FAILED\",\n      \"allocationState\": \"FAILED\",\n      \"executableState\": \"FAILED\",\n      \"isWritable\": true,\n      \"isProvidable\": true,\n      \"notifyParticipants\": true,\n      \"ownerName\": \"Michal Drobnak\",\n      \"ownerEmail\": \"493239@muni.cz\",\n      \"slot\": {\n        \"start\": \"2021-11-04T15:30:00.000Z\",\n        \"end\": \"2021-11-04T16:30:00.000Z\"\n      },\n      \"periodicity\": {\n        \"type\": \"DAILY\",\n        \"periodicityEnd\": \"2021-11-04T15:30:00.000Z\",\n        \"excludeDates\": [\n          \"2021-11-04\"\n        ]\n      },\n      \"futureSlotCount\": 5,\n      \"isDeprecated\": false,\n      \"type\": \"PHYSICAL_RESOURCE\",\n      \"physicalResourceData\": {\n        \"resourceName\": \"Gotex zasedacka G314\",\n        \"resourceDescription\": \"Zasedací místnost\\nv budově GOTEXu.\"\n      },\n      \"history\": [\n        {\n          \"id\": \"shongo:meetings.cesnet.cz:req:2\",\n          \"createdAt\": \"2021-11-03T18:38:09.546Z\",\n          \"createdBy\": \"Michal Drobnak\",\n          \"type\": \"NEW\",\n          \"allocationState\": \"ERROR\",\n          \"state\": \"ERROR\",\n          \"isActive\": true,\n          \"isLatestAllocated\": true\n        }\n      ]\n    }\n  {{/ case}}\n  {{# case \"shongo:meetings.cesnet.cz:req:3\" }}\n    {\n      \"id\": \"shongo:meetings.cesnet.cz:req:3\",\n      \"description\": \"A virtual room reservation.\",\n      \"createdAt\": \"2021-11-03T18:38:09.546Z\",\n      \"state\": \"FAILED\",\n      \"allocationState\": \"FAILED\",\n      \"executableState\": \"FAILED\",\n      \"isWritable\": true,\n      \"isProvidable\": true,\n      \"notifyParticipants\": true,\n      \"ownerName\": \"Michal Drobnak\",\n      \"ownerEmail\": \"493239@muni.cz\",\n      \"slot\": {\n        \"start\": \"2021-11-04T15:30:00.000Z\",\n        \"end\": \"2021-11-04T16:30:00.000Z\"\n      },\n      \"periodicity\": {\n        \"type\": \"MONTHLY\",\n        \"monthlyPeriodicityType\": \"SPECIFIC_DAY\",\n        \"periodicityEnd\": \"2021-11-04T15:30:00.000Z\",\n        \"periodicDayInMonth\": \"MONDAY\",\n        \"periodicityDayOrder\": 2,\n        \"periodicityCycle\": 1,\n        \"excludeDates\": [\n          \"2021-11-04\"\n        ]\n      },\n      \"isDeprecated\": false,\n      \"type\": \"ROOM_CAPACITY\",\n      \"roomCapacityData\": {\n        \"roomName\": \"Some room\",\n        \"roomReservationRequestId\": \"shongo:meetings.cesnet.cz:req:1\",\n        \"roomParticipantCount\": 5\n      },\n      \"authorizedData\": {\n        \"pin\": \"12345\",\n        \"adminPin\": \"56789\",\n        \"guestPin\": \"478\",\n        \"allowGuests\": true,\n        \"aliases\": {\n          \"H323/SIP/PhoneNumber\": \"(00420)950087050\",\n          \"H.323 IP\": \"78.128.216.82 050#\"\n        }\n      },\n      \"history\": [\n        {\n          \"id\": \"shongo:meetings.cesnet.cz:req:3\",\n          \"createdAt\": \"2021-11-03T18:38:09.546Z\",\n          \"createdBy\": \"Michal Drobnak\",\n          \"type\": \"NEW\",\n          \"allocationState\": \"ERROR\",\n          \"state\": \"ERROR\",\n          \"isActive\": true,\n          \"isLatestAllocated\": true\n        }\n      ]\n    }\n  {{/ case}}\n  {{# case \"shongo:meetings.cesnet.cz:req:4\" }}\n    {\n      \"id\": \"shongo:meetings.cesnet.cz:req:4\",\n      \"description\": \"A virtual room reservation.\",\n      \"createdAt\": \"2021-11-03T18:38:09.546Z\",\n      \"state\": \"FAILED\",\n      \"allocationState\": \"FAILED\",\n      \"executableState\": \"FAILED\",\n      \"isWritable\": true,\n      \"isProvidable\": true,\n      \"notifyParticipants\": true,\n      \"ownerName\": \"Michal Drobnak\",\n      \"ownerEmail\": \"493239@muni.cz\",\n      \"slot\": {\n        \"start\": \"2021-11-04T15:30:00.000Z\",\n        \"end\": \"2021-11-04T16:30:00.000Z\"\n      },\n      \"periodicity\": {\n        \"type\": \"MONTHLY\",\n        \"monthlyPeriodicityType\": \"SPECIFIC_DAY\",\n        \"periodicityEnd\": \"2021-11-04T15:30:00.000Z\",\n        \"periodicDayInMonth\": \"MONDAY\",\n        \"periodicityDayOrder\": -1,\n        \"periodicityCycle\": 1,\n        \"excludeDates\": [\n          \"2021-11-04\",\n          \"2021-11-05\"\n        ]\n      },\n      \"futureSlotCount\": 5,\n      \"isDeprecated\": false,\n      \"type\": \"VIRTUAL_ROOM\",\n      \"virtualRoomData\": {\n        \"technology\": \"PEXIP\",\n        \"roomName\": \"Some room\",\n        \"roomParticipantCount\": 5,\n        \"roomHasRecordingService\": true,\n        \"roomHasRecordings\": false,\n        \"isRecordingActive\": false\n      },\n      \"authorizedData\": {\n        \"pin\": \"12345\",\n        \"adminPin\": \"56789\",\n        \"guestPin\": \"478\",\n        \"allowGuests\": true,\n        \"aliases\": {\n          \"H323/SIP/PhoneNumber\": \"(00420)950087050\",\n          \"H.323 IP\": \"78.128.216.82 050#\"\n        }\n      },\n      \"history\": [\n        {\n          \"id\": \"shongo:meetings.cesnet.cz:req:4\",\n          \"createdAt\": \"2021-11-03T18:38:09.546Z\",\n          \"createdBy\": \"Michal Drobnak\",\n          \"type\": \"NEW\",\n          \"allocationState\": \"ERROR\",\n          \"state\": \"ERROR\",\n          \"isActive\": true,\n          \"isLatestAllocated\": true\n        }\n      ]\n    }\n  {{/ case}}\n  {{# case \"shongo:meetings.cesnet.cz:req:3\" }}\n    {\n      \"id\": \"shongo:meetings.cesnet.cz:req:3\",\n      \"description\": \"A virtual room reservation.\",\n      \"createdAt\": \"2021-11-03T18:38:09.546Z\",\n      \"state\": \"FAILED\",\n      \"allocationState\": \"FAILED\",\n      \"executableState\": \"FAILED\",\n      \"isWritable\": true,\n      \"isProvidable\": true,\n      \"notifyParticipants\": true,\n      \"ownerName\": \"Michal Drobnak\",\n      \"ownerEmail\": \"493239@muni.cz\",\n      \"slot\": {\n        \"start\": \"2021-11-04T15:30:00.000Z\",\n        \"end\": \"2021-11-04T16:30:00.000Z\"\n      },\n      \"periodicity\": {\n        \"type\": \"MONTHLY\",\n        \"monthlyPeriodicityType\": \"SPECIFIC_DAY\",\n        \"periodicityEnd\": \"2021-11-04T15:30:00.000Z\",\n        \"periodicDayInMonth\": \"MONDAY\",\n        \"periodicityDayOrder\": 2,\n        \"periodicityCycle\": 1,\n        \"excludeDates\": [\n          \"2021-11-04\"\n        ]\n      },\n      \"futureSlotCount\": 5,\n      \"isDeprecated\": false,\n      \"type\": \"ROOM_CAPACITY\",\n      \"roomCapacityData\": {\n        \"roomName\": \"Some room\",\n        \"roomReservationRequestId\": \"shongo:meetings.cesnet.cz:req:1\",\n        \"roomParticipantCount\": 5\n      },\n      \"authorizedData\": {\n        \"pin\": \"12345\",\n        \"adminPin\": \"56789\",\n        \"guestPin\": \"478\",\n        \"allowGuests\": true,\n        \"aliases\": {\n          \"H323/SIP/PhoneNumber\": \"(00420)950087050\",\n          \"H.323 IP\": \"78.128.216.82 050#\"\n        }\n      },\n      \"history\": [\n        {\n          \"id\": \"shongo:meetings.cesnet.cz:req:3\",\n          \"createdAt\": \"2021-11-03T18:38:09.546Z\",\n          \"createdBy\": \"Michal Drobnak\",\n          \"type\": \"NEW\",\n          \"allocationState\": \"ERROR\",\n          \"state\": \"ERROR\",\n          \"isActive\": true,\n          \"isLatestAllocated\": true\n        }\n      ]\n    }\n  {{/ case}}\n  {{# case \"shongo:meetings.cesnet.cz:req:5\" }}\n    {\n      \"id\": \"shongo:meetings.cesnet.cz:req:5\",\n      \"description\": \"Modified reservation request.\",\n      \"createdAt\": \"2021-11-04T15:21:00.546Z\",\n      \"state\": \"FAILED\",\n      \"allocationState\": \"FAILED\",\n      \"executableState\": \"FAILED\",\n      \"isWritable\": true,\n      \"isProvidable\": true,\n      \"notifyParticipants\": true,\n      \"ownerName\": \"Michal Drobnak\",\n      \"ownerEmail\": \"493239@muni.cz\",\n      \"slot\": {\n        \"start\": \"2021-11-04T15:30:00.000Z\",\n        \"end\": \"2021-11-04T16:30:00.000Z\"\n      },\n      \"periodicity\": {\n        \"type\": \"MONTHLY\",\n        \"monthlyPeriodicityType\": \"SPECIFIC_DAY\",\n        \"periodicityEnd\": \"2021-11-04T15:30:00.000Z\",\n        \"periodicDayInMonth\": \"MONDAY\",\n        \"periodicityDayOrder\": -1,\n        \"periodicityCycle\": 1,\n        \"excludeDates\": [\n          \"2021-11-04\",\n          \"2021-11-05\"\n        ]\n      },\n      \"futureSlotCount\": 5,\n      \"isDeprecated\": false,\n      \"type\": \"VIRTUAL_ROOM\",\n      \"virtualRoomData\": {\n        \"technology\": \"PEXIP\",\n        \"roomName\": \"Some room\",\n        \"roomParticipantCount\": 5,\n        \"roomHasRecordingService\": true,\n        \"roomHasRecordings\": false,\n        \"isRecordingActive\": false\n      },\n      \"authorizedData\": {\n        \"pin\": \"12345\",\n        \"adminPin\": \"56789\",\n        \"guestPin\": \"478\",\n        \"allowGuests\": true,\n        \"aliases\": {\n          \"H323/SIP/PhoneNumber\": \"(00420)950087050\",\n          \"H.323 IP\": \"78.128.216.82 050#\"\n        }\n      }\n    }\n  {{/ case}}\n{{/ switch }}",
          "latency": 0,
          "statusCode": 200,
          "label": "",
          "headers": [],
          "filePath": "",
          "sendFileAsBody": false,
          "rules": [],
          "rulesOperator": "OR",
          "disableTemplating": false,
          "fallbackTo404": false
        }
      ],
      "enabled": true,
      "randomResponse": false,
      "sequentialResponse": false
    },
    {
      "uuid": "39239367-0554-4075-9d6a-1402e1ec5cc4",
      "documentation": "",
      "method": "delete",
      "endpoint": "reservation_requests/:id",
      "responses": [
        {
          "uuid": "c4ff0133-d589-4508-b133-451d3e01f73b",
          "body": "{}",
          "latency": 0,
          "statusCode": 200,
          "label": "",
          "headers": [],
          "filePath": "",
          "sendFileAsBody": false,
          "rules": [],
          "rulesOperator": "OR",
          "disableTemplating": false,
          "fallbackTo404": false
        }
      ],
      "enabled": true,
      "randomResponse": false,
      "sequentialResponse": false
    },
    {
      "uuid": "54d599e9-8f97-4684-9014-f7eee7ee811e",
      "documentation": "",
      "method": "post",
      "endpoint": "reservation_requests/:id/revert",
      "responses": [
        {
          "uuid": "24b20a4b-b3f3-44f2-baae-5ac1aee5cd68",
          "body": "{}",
          "latency": 0,
          "statusCode": 200,
          "label": "",
          "headers": [],
          "filePath": "",
          "sendFileAsBody": false,
          "rules": [],
          "rulesOperator": "OR",
          "disableTemplating": false,
          "fallbackTo404": false
        }
      ],
      "enabled": true,
      "randomResponse": false,
      "sequentialResponse": false
    },
    {
      "uuid": "bd8588dc-a212-4ea9-b9ab-37731710ddfa",
      "documentation": "",
      "method": "get",
      "endpoint": "reservation_requests/:id/participants",
      "responses": [
        {
          "uuid": "c44a6c3a-25e6-4e59-a45e-14937386a099",
          "body": "{\n  \"count\": 1,\n  \"items\": [\n    {\n      \"id\": \"1340622\",\n      \"type\": \"USER\",\n      \"name\": \"Michal Drobnak\",\n      \"email\": \"493239@mail.muni.cz\",\n      \"organization\": \"Masarykova Univerzita\",\n      \"role\": \"ADMINISTRATOR\"\n    }  \n  ]\n}",
          "latency": 0,
          "statusCode": 200,
          "label": "",
          "headers": [],
          "filePath": "",
          "sendFileAsBody": false,
          "rules": [],
          "rulesOperator": "OR",
          "disableTemplating": false,
          "fallbackTo404": false
        }
      ],
      "enabled": true,
      "randomResponse": false,
      "sequentialResponse": false
    },
    {
      "uuid": "b4c58465-b9f0-41eb-ba50-6581afc2f92f",
      "documentation": "",
      "method": "delete",
      "endpoint": "reservation_requests/:id/participants/:participantId",
      "responses": [
        {
          "uuid": "8a640bf8-25ce-4b49-92fd-05cbb45a0bba",
          "body": "{}",
          "latency": 0,
          "statusCode": 200,
          "label": "",
          "headers": [],
          "filePath": "",
          "sendFileAsBody": false,
          "rules": [],
          "rulesOperator": "OR",
          "disableTemplating": false,
          "fallbackTo404": false
        }
      ],
      "enabled": true,
      "randomResponse": false,
      "sequentialResponse": false
    },
    {
      "uuid": "351a7e17-2a2e-411c-a395-3fd96ae77f4f",
      "documentation": "",
      "method": "put",
      "endpoint": "reservation_requests/:objectId/participants/:participantId",
      "responses": [
        {
          "uuid": "efc678c3-1502-4fa1-9fde-a81fd03cfe37",
          "body": "{\n  \"role\": \"ADMINISTRATOR\"\n}",
          "latency": 0,
          "statusCode": 200,
          "label": "",
          "headers": [],
          "filePath": "",
          "sendFileAsBody": false,
          "rules": [],
          "rulesOperator": "OR",
          "disableTemplating": false,
          "fallbackTo404": false
        }
      ],
      "enabled": true,
      "randomResponse": false,
      "sequentialResponse": false
    },
    {
      "uuid": "b04cb3a6-5578-44f3-b5b7-6c180b47486b",
      "documentation": "",
      "method": "get",
      "endpoint": "reservation_requests/:id/roles",
      "responses": [
        {
          "uuid": "83754e0c-aa58-48d0-adc5-9017c4191d2e",
          "body": "{\n  \"count\": 1,\n  \"items\": [\n    {\n      \"identityType\": \"GROUP\",\n      \"identityPrincipalId\": \"s1ad65w1f96w51fq95w1f6a2s1d6as5d16a@einfra.cesnet.cz\",\n      \"identityName\": \"UVT\",\n      \"identityDescription\": \"Ustav vypocetni techniky\",\n      \"role\": \"OWNER\",\n      \"deletable\": false\n    },\n    {\n      \"identityType\": \"USER\",\n      \"identityPrincipalId\": \"asda65s1d6as1d98a1sf9as1fas6d5as6d1@einfra.cesnet.cz\",\n      \"identityName\": \"Michal Drobňák\",\n      \"identityDescription\": \"Masarykova univerzita\",\n      \"role\": \"OWNER\",\n      \"email\": \"493239@muni.cz\",\n      \"deletable\": true\n    }  \n  ]\n}",
          "latency": 0,
          "statusCode": 200,
          "label": "",
          "headers": [],
          "filePath": "",
          "sendFileAsBody": false,
          "rules": [],
          "rulesOperator": "OR",
          "disableTemplating": false,
          "fallbackTo404": false
        }
      ],
      "enabled": true,
      "randomResponse": false,
      "sequentialResponse": false
    },
    {
      "uuid": "76ec1a20-809c-4e45-b23a-a9504ea3ca4a",
      "documentation": "",
      "method": "delete",
      "endpoint": "reservation_requests/:id/roles/:identityPrincipalId",
      "responses": [
        {
          "uuid": "3bd78613-11db-435f-b820-9e6e78d1e762",
          "body": "{}",
          "latency": 0,
          "statusCode": 200,
          "label": "",
          "headers": [],
          "filePath": "",
          "sendFileAsBody": false,
          "rules": [],
          "rulesOperator": "OR",
          "disableTemplating": false,
          "fallbackTo404": false
        }
      ],
      "enabled": true,
      "randomResponse": false,
      "sequentialResponse": false
    },
    {
      "uuid": "cc940f04-cf42-43d8-8dee-7ff344b3e8bf",
      "documentation": "",
      "method": "post",
      "endpoint": "reservation_requests/:id/roles",
      "responses": [
        {
          "uuid": "5d58dd3a-b0ba-4dcc-b262-8dd7f6742535",
          "body": "{\n  \"type\": \"GROUP\",\n  \"entityId\": \"1\",\n  \"role\": \"OWNER\"\n}",
          "latency": 0,
          "statusCode": 200,
          "label": "",
          "headers": [],
          "filePath": "",
          "sendFileAsBody": false,
          "rules": [],
          "rulesOperator": "OR",
          "disableTemplating": false,
          "fallbackTo404": false
        }
      ],
      "enabled": true,
      "randomResponse": false,
      "sequentialResponse": false
    },
    {
      "uuid": "f346d09c-1990-40a5-b322-f0241ee77fc0",
      "documentation": "Duration field is in milliseconds.",
      "method": "get",
      "endpoint": "reservation_requests/:id/recordings",
      "responses": [
        {
          "uuid": "b471a50e-9bbf-48d3-94a8-cffb98b284b1",
          "body": "{\n  \"count\": 1,\n  \"items\": [\n    {\n      \"id\": \"shongo:meetings.cesnet.cz:rec:1\",\n      \"resourceId\": \"shongo:meetings.cesnet.cz:res:1\",\n      \"name\": \"My recording\",\n      \"description\": \"Recording description\",\n      \"isPublic\": true,\n      \"beginDate\": \"2021-11-03T18:38:09.546Z\",\n      \"duration\": 7200000,\n      \"downloadUrl\": \"http://localhost\",\n      \"viewUrl\": \"https://www.youtube.com/\",\n      \"editUrl\": \"http://localhost\",\n      \"filename\": \"Videoconference:2020-19-05T11:29:40Z.mp4\"\n    }\n  ]\n}",
          "latency": 0,
          "statusCode": 200,
          "label": "",
          "headers": [],
          "filePath": "",
          "sendFileAsBody": false,
          "rules": [],
          "rulesOperator": "OR",
          "disableTemplating": false,
          "fallbackTo404": false
        }
      ],
      "enabled": true,
      "randomResponse": false,
      "sequentialResponse": false
    },
    {
      "uuid": "82f777f3-7678-4119-9ec9-5ec988fc4ab8",
      "documentation": "",
      "method": "delete",
      "endpoint": "reservation_requests/:objectId/recordings/:recordingId",
      "responses": [
        {
          "uuid": "8ac35685-afa2-4d53-ac2d-96efc7d2cdc7",
          "body": "{}",
          "latency": 0,
          "statusCode": 200,
          "label": "",
          "headers": [],
          "filePath": "",
          "sendFileAsBody": false,
          "rules": [],
          "rulesOperator": "OR",
          "disableTemplating": false,
          "fallbackTo404": false
        }
      ],
      "enabled": true,
      "randomResponse": false,
      "sequentialResponse": false
    },
    {
      "uuid": "bb9cbd5d-9b52-4358-9e19-b0ca1ee5c03d",
      "documentation": "",
      "method": "get",
      "endpoint": "reservation_requests/:id/runtime_management/participants",
      "responses": [
        {
          "uuid": "27a7bc2f-5209-44df-a68d-9d2b0302aefd",
          "body": "{\n  \"count\": 1,\n  \"items\": [\n    {\n      \"id\": \"1\",\n      \"name\": \"Michal Drobnak\",\n      \"displayName\": \"fancy_pants123\",\n      \"role\": \"ADMIN\",\n      \"alias\": \"ROOM_NAME\",\n      \"email\": \"463239@muni.cz\",\n      \"layout\": \"SPEAKER\",\n      \"microphoneEnabled\": true,\n      \"microphoneLevel\": 10,\n      \"videoEnabled\": true,\n      \"videoSnapshot\": true\n    }\n  ]\n}",
          "latency": 0,
          "statusCode": 200,
          "label": "",
          "headers": [],
          "filePath": "",
          "sendFileAsBody": false,
          "rules": [],
          "rulesOperator": "OR",
          "disableTemplating": false,
          "fallbackTo404": false
        }
      ],
      "enabled": true,
      "randomResponse": false,
      "sequentialResponse": false
    },
    {
      "uuid": "a7bbf248-5ee0-490f-a718-dfe60dc506ca",
      "documentation": "Returns a photo of participant.",
      "method": "get",
      "endpoint": "reservation_requests/:objectId/runtime_management/participants/:participantId/snapshot",
      "responses": [
        {
          "uuid": "82e64703-3e39-4523-9e0c-db6543568742",
          "body": "",
          "latency": 0,
          "statusCode": 500,
          "label": "",
          "headers": [
            {
              "key": "Cache-Control",
              "value": "no-cache, no-store, must-revalidate"
            },
            {
              "key": "Pragma",
              "value": "no-cache"
            }
          ],
          "filePath": "./assets/zoom.jpg",
          "sendFileAsBody": true,
          "rules": [],
          "rulesOperator": "OR",
          "disableTemplating": false,
          "fallbackTo404": false
        }
      ],
      "enabled": true,
      "randomResponse": false,
      "sequentialResponse": false
    },
    {
      "uuid": "cee4d8f4-ad6c-4fa7-8835-bd4207acb5cf",
      "documentation": "Takes partial JSON data to update participant.",
      "method": "patch",
      "endpoint": "reservation_requests/:objectId/runtime_management/participants/:participantId",
      "responses": [
        {
          "uuid": "75daf295-1510-4785-92aa-fa7a9faf2b9a",
          "body": "{}",
          "latency": 0,
          "statusCode": 200,
          "label": "",
          "headers": [],
          "filePath": "",
          "sendFileAsBody": false,
          "rules": [],
          "rulesOperator": "OR",
          "disableTemplating": false,
          "fallbackTo404": false
        }
      ],
      "enabled": true,
      "randomResponse": false,
      "sequentialResponse": false
    },
    {
      "uuid": "a2e8947d-3fed-499a-ba70-dc2ae6648fe3",
      "documentation": "",
      "method": "post",
      "endpoint": "reservation_requests/:objectId/runtime_management/participants/:participantId/disconnect",
      "responses": [
        {
          "uuid": "1141f4b2-69a3-4e37-9d20-88f4752739d9",
          "body": "{}",
          "latency": 0,
          "statusCode": 200,
          "label": "",
          "headers": [],
          "filePath": "",
          "sendFileAsBody": false,
          "rules": [],
          "rulesOperator": "OR",
          "disableTemplating": false,
          "fallbackTo404": false
        }
      ],
      "enabled": true,
      "randomResponse": false,
      "sequentialResponse": false
    },
    {
      "uuid": "146be260-68d0-49d3-aa81-0aa25128c860",
      "documentation": "",
      "method": "post",
      "endpoint": "reservation_requests/:objectId/runtime_management/recording/start",
      "responses": [
        {
          "uuid": "c6a07f12-bdf8-4098-b33b-3c71c78f046b",
          "body": "{}",
          "latency": 0,
          "statusCode": 200,
          "label": "",
          "headers": [],
          "filePath": "",
          "sendFileAsBody": false,
          "rules": [],
          "rulesOperator": "OR",
          "disableTemplating": false,
          "fallbackTo404": false
        }
      ],
      "enabled": true,
      "randomResponse": false,
      "sequentialResponse": false
    },
    {
      "uuid": "28f65191-11ed-46df-82b0-0c2a0aae32f1",
      "documentation": "",
      "method": "post",
      "endpoint": "reservation_requests/:objectId/runtime_management/recording/stop",
      "responses": [
        {
          "uuid": "46260b8a-57e2-4e75-916b-a1b3ddf4ee01",
          "body": "{}",
          "latency": 0,
          "statusCode": 200,
          "label": "",
          "headers": [],
          "filePath": "",
          "sendFileAsBody": false,
          "rules": [],
          "rulesOperator": "OR",
          "disableTemplating": false,
          "fallbackTo404": false
        }
      ],
      "enabled": true,
      "randomResponse": false,
      "sequentialResponse": false
    },
    {
      "uuid": "9d8e37e7-6055-4df6-917e-104f30b1888a",
      "documentation": "",
      "method": "post",
      "endpoint": "reservation_requests/:id/user_participant",
      "responses": [
        {
          "uuid": "6af79010-9df3-4a42-aab2-d22f04805b6e",
          "body": "{\n  \"userId\": \"as1da81d9w8da9d51sa65da1s9d@einfra.cesnet.cz\",\n  \"role\": \"PARTICIPANT\"\n}",
          "latency": 0,
          "statusCode": 200,
          "label": "",
          "headers": [],
          "filePath": "",
          "sendFileAsBody": false,
          "rules": [],
          "rulesOperator": "OR",
          "disableTemplating": false,
          "fallbackTo404": false
        }
      ],
      "enabled": true,
      "randomResponse": false,
      "sequentialResponse": false
    },
    {
      "uuid": "51eac132-fa63-40f4-9b62-5f90bb14009d",
      "documentation": "",
      "method": "post",
      "endpoint": "reservation_requests/:id/guest_participant",
      "responses": [
        {
          "uuid": "3e00b2d8-1aaa-4846-89bb-22f8e50b19d6",
          "body": "{\n  \"name\": \"Michal\",\n  \"email\": \"idk@gmail.com\"\n}",
          "latency": 0,
          "statusCode": 200,
          "label": "",
          "headers": [],
          "filePath": "",
          "sendFileAsBody": false,
          "rules": [],
          "rulesOperator": "OR",
          "disableTemplating": false,
          "fallbackTo404": false
        }
      ],
      "enabled": true,
      "randomResponse": false,
      "sequentialResponse": false
    },
    {
      "uuid": "b64ded97-11b2-4ba4-94fd-875ac156514d",
      "documentation": "Rooms are reservation requests scheduled by a scheduler, they become executables after scheduling.",
      "method": "get",
      "endpoint": "rooms",
      "responses": [
        {
          "uuid": "6fc1ce63-1b85-4ab5-92cf-b01efb2658dc",
          "body": "{\n  \"count\": 1,\n  \"items\": [\n    { \n      \"id\": \"1\",\n      \"type\": \"ROOM\",\n      \"slot\": {\n        \"start\": \"2021-11-04T15:30:00.000Z\",\n        \"end\": \"2021-11-04T16:30:00.000Z\"\n      },\n      \"earliestSlot\": {\n        \"start\": \"2021-11-04T15:30:00.000Z\",\n        \"end\": \"2021-11-04T16:30:00.000Z\"\n      },\n      \"description\": \"Testing room\",\n      \"name\": \"Testing room\",\n      \"technology\": \"PEXIP\",\n      \"state\": \"FAILED\",\n      \"isAvailable\": false,\n      \"isDeprecated\": false,\n      \"licenceCount\": 10,\n      \"usageCount\": 8\n    }\n  ]\n}",
          "latency": 0,
          "statusCode": 200,
          "label": "",
          "headers": [],
          "filePath": "",
          "sendFileAsBody": false,
          "rules": [],
          "rulesOperator": "OR",
          "disableTemplating": false,
          "fallbackTo404": false
        }
      ],
      "enabled": true,
      "randomResponse": false,
      "sequentialResponse": false
    },
    {
      "uuid": "39daccc3-5fde-4390-9bc3-307022d36e7e",
      "documentation": "",
      "method": "get",
      "endpoint": "resources/capacity_utilizations",
      "responses": [
        {
          "uuid": "4ed211b6-b3aa-44c2-a24a-295d70215dc1",
          "body": "{\n  \"count\": 1,\n  \"items\": [\n    {\n      \"intervalFrom\": \"2021-11-03T18:38:09.546Z\",\n      \"intervalTo\": \"2021-11-03T18:38:09.546Z\",\n      \"resources\": [\n        {\n          \"id\": \"shongo:meetings.cesnet.cz:res:42\",\n          \"name\": \"Pexip\",\n          \"totalCapacity\": 80,\n          \"usedCapacity\": 79\n        },\n        {\n          \"id\": \"shongo:meetings.cesnet.cz:res:43\",\n          \"name\": \"tcs2\",\n          \"totalCapacity\": 100,\n          \"usedCapacity\": 8\n        },\n        {\n          \"id\": \"shongo:meetings.cesnet.cz:res:44\",\n          \"name\": \"connect-cesnet-new\",\n          \"totalCapacity\": 95,\n          \"usedCapacity\": 30\n        },\n        {\n          \"id\": \"shongo:meetings.cesnet.cz:res:45\",\n          \"name\": \"mcu-cesnet\",\n          \"totalCapacity\": 20,\n          \"usedCapacity\": 8\n        },\n        {\n          \"id\": \"shongo:meetings.cesnet.cz:res:46\",\n          \"name\": \"mcu-muni\",\n          \"totalCapacity\": 33,\n          \"usedCapacity\": 11\n        },\n        {\n          \"id\": \"shongo:meetings.cesnet.cz:res:47\",\n          \"name\": \"connect-cesnet-old\",\n          \"totalCapacity\": 158,\n          \"usedCapacity\": 78\n        },\n        {\n          \"id\": \"shongo:meetings.cesnet.cz:res:48\",\n          \"name\": \"FreePBX-UVT\",\n          \"totalCapacity\": 44,\n          \"usedCapacity\": 3\n        }\n      ]\n    }  \n  ]\n}",
          "latency": 0,
          "statusCode": 200,
          "label": "",
          "headers": [],
          "filePath": "",
          "sendFileAsBody": false,
          "rules": [],
          "rulesOperator": "OR",
          "disableTemplating": false,
          "fallbackTo404": false
        }
      ],
      "enabled": true,
      "randomResponse": false,
      "sequentialResponse": false
    },
    {
      "uuid": "078d3a16-3a02-4915-949c-904990f9574a",
      "documentation": "",
      "method": "get",
      "endpoint": "resources/:id/capacity_utilizations",
      "responses": [
        {
          "uuid": "307b1ede-49ba-4298-b654-e1e8647230fa",
          "body": "{\n  \"id\": \"shongo:meetings.cesnet.cz:res:42\",\n  \"name\": \"Pexip\",\n  \"intervalFrom\": \"2021-11-03T18:38:09.546Z\",\n  \"intervalTo\": \"2021-11-03T18:38:09.546Z\",\n  \"totalCapacity\": 50,\n  \"usedCapacity\": 5,\n  \"reservations\": [\n    {\n      \"id\": \"shongo:meetings.cesnet.cz:rsv:80\",\n      \"slot\": {\n        \"start\": \"2021-11-03T18:38:09.546Z\",\n        \"end\": \"2021-11-03T18:38:09.546Z\"\n      },\n      \"licenceCount\": 5,\n      \"requestId\": \"shongo:meetings.cesnet.cz:req:62\",\n      \"user\": {\n        \"id\": \"65asd65as6f51aw89f1a6s51da3s1d@einfra.cesnet.cz\",\n        \"name\": \"Michal Drobnak\",\n        \"email\": \"493239@mail.muni.cz\"\n      }\n    }\n  ]\n}",
          "latency": 0,
          "statusCode": 200,
          "label": "",
          "headers": [],
          "filePath": "",
          "sendFileAsBody": false,
          "rules": [],
          "rulesOperator": "OR",
          "disableTemplating": false,
          "fallbackTo404": false
        }
      ],
      "enabled": true,
      "randomResponse": false,
      "sequentialResponse": false
    },
    {
      "uuid": "35343572-70ef-4c9e-af00-318aeb2361ef",
      "documentation": "Returns list of SystemPermission that requesting user has",
      "method": "get",
      "endpoint": "permissions",
      "responses": [
        {
          "uuid": "47f695e2-2cdd-41dd-8b36-e6b77dfc6269",
          "body": "[\n  ADMINISTRATOR,\n  OPERATOR,\n  RESERVATION\n]",
          "latency": 0,
          "statusCode": 200,
          "label": "",
          "headers": [],
          "filePath": "",
          "sendFileAsBody": false,
          "rules": [],
          "rulesOperator": "OR",
          "disableTemplating": false,
          "fallbackTo404": false
        }
      ],
      "enabled": true,
      "randomResponse": false,
      "sequentialResponse": false
    },
    {
      "uuid": "e4f66f95-c031-4b0c-825f-30f5b945dc95",
      "documentation": "",
      "method": "get",
      "endpoint": "users",
      "responses": [
        {
          "uuid": "64ce6cfe-ec57-4299-b52d-63e61444df0b",
          "body": "{\n  \"count\": 1,\n  \"items\": [\n    {\n      \"userId\": \"1430cff140c2ce0a0c6751f130af3224b80306b9@einfra.cesnet.cz\",\n      \"principalNames\": [\n        \"1430cff140c2ce0a0c6751f130af3224b80306b9@einfra.cesnet.cz\",\n        \"492598@muni.cz\"\n      ],\n      \"firstName\": \"Filip\",\n      \"lastName\": \"Karniš\",\n      \"organization\": \"Masarykova univerzita\",\n      \"email\": \"492598@mail.muni.cz\",\n      \"fullName\": \"Filip Karniš\",\n      \"locale\": null,\n      \"zoneInfo\": null,\n      \"eduPersonEntitlement\": [],\n      \"rootOrganization\": \"Masarykova univerzita\",\n      \"primaryEmail\": \"492598@mail.muni.cz\",\n      \"className\": \"UserInformation\"\n    }\n  ]\n}",
          "latency": 0,
          "statusCode": 200,
          "label": "",
          "headers": [],
          "filePath": "",
          "sendFileAsBody": false,
          "rules": [],
          "rulesOperator": "OR",
          "disableTemplating": false,
          "fallbackTo404": false
        }
      ],
      "enabled": true,
      "randomResponse": false,
      "sequentialResponse": false
    },
    {
      "uuid": "3e81f8e0-7700-4cd3-ae8f-c22aee367ceb",
      "documentation": "",
      "method": "put",
      "endpoint": "users/settings",
      "responses": [
        {
          "uuid": "be9c8bcf-cd5f-435b-8f3b-6a6ff168022b",
          "body": "{\n  \"usePerunSettings\": false,\n  \"language\": \"en\",\n  \"timeZone\": \"Pacific/Wake\"\n}",
          "latency": 0,
          "statusCode": 200,
          "label": "",
          "headers": [],
          "filePath": "",
          "sendFileAsBody": false,
          "rules": [],
          "rulesOperator": "OR",
          "disableTemplating": false,
          "fallbackTo404": false
        }
      ],
      "enabled": true,
      "randomResponse": false,
      "sequentialResponse": false
    },
    {
      "uuid": "e4c1adeb-97a8-4674-b7a8-e3d86cb836bb",
      "documentation": "",
      "method": "get",
      "endpoint": "groups",
      "responses": [
        {
          "uuid": "0b55274f-9528-4a5c-b53a-0e6108ca3e96",
          "body": "{\n  \"count\": 1,\n  \"items\": [\n    {\n      \"id\": \"einfra:projects:shongo:users:uvt\",\n      \"parentGroupId\": null,\n      \"name\": \"uvt\",\n      \"description\": \"Skupina obsahující lidi z UVT\",\n      \"administrators\": [],\n      \"secondaryId\": null\n    }\n  ]\n}",
          "latency": 0,
          "statusCode": 200,
          "label": "",
          "headers": [],
          "filePath": "",
          "sendFileAsBody": false,
          "rules": [],
          "rulesOperator": "OR",
          "disableTemplating": false,
          "fallbackTo404": false
        }
      ],
      "enabled": true,
      "randomResponse": false,
      "sequentialResponse": false
    }
  ],
  "proxyMode": false,
  "proxyHost": "",
  "proxyRemovePrefix": false,
  "tlsOptions": {
    "enabled": false,
    "type": "CERT",
    "pfxPath": "",
    "certPath": "",
    "keyPath": "",
    "caPath": "",
    "passphrase": ""
  },
  "cors": true,
  "headers": [
    {
      "key": "Content-Type",
      "value": "application/json"
    },
    {
      "key": "Access-Control-Allow-Origin",
      "value": "*"
    },
    {
      "key": "Access-Control-Allow-Methods",
      "value": "GET,POST,PUT,PATCH,DELETE,HEAD,OPTIONS"
    },
    {
      "key": "Access-Control-Allow-Headers",
      "value": "Content-Type, Origin, Accept, Authorization, Content-Length, X-Requested-With"
    }
  ],
  "proxyReqHeaders": [
    {
      "key": "",
      "value": ""
    }
  ],
  "proxyResHeaders": [
    {
      "key": "",
      "value": ""
    }
  ]
}